iderare_pheno/__init__.py
iderare_pheno/converter.py
iderare_pheno/fhir_parser.py
iderare_pheno/py.typed
iderare_pheno/simrec.py
iderare_pheno/streamlit_utils.py
iderare_pheno/utils.py
iderare_pheno/version.py
iderare_pheno/phenotype/data/genes_to_phenotype.txt
iderare_pheno/phenotype/data/hp.obo
iderare_pheno/phenotype/data/phenotype.hpoa
iderare_pheno/phenotype/subset/icd102omim_subset.tsv
iderare_pheno/phenotype/subset/loinc2hpo_standardized.tsv
iderare_pheno/phenotype/subset/omim2hpo_subset.tsv
iderare_pheno/phenotype/subset/orpha2hpo_subset.tsv
iderare_pheno/phenotype/subset/orpha2omim_subset.tsv
iderare_pheno/phenotype/subset/snomed2hpo_subset.tsv
iderare_pheno/phenotype/subset/snomed2orpha_subset.tsv
iderare_pheno/templates/template_iderare.yml
iderare_pheno-0.7.3.dist-info/LICENSE
iderare_pheno-0.7.3.dist-info/METADATA
iderare_pheno-0.7.3.dist-info/WHEEL
iderare_pheno-0.7.3.dist-info/top_level.txt
iderare_pheno-0.7.3.dist-info/RECORD
