Metadata-Version: 2.2
Name: iderare-pheno
Version: 0.7.3
Author-email: Ivan William Harsono <ivanwilliam.md@gmail.com>
License: BSD 3-Clause License
Project-URL: Homepage, https://github.com/ivanwilliammd/iderare-pheno
Project-URL: Repository, https://github.com/ivanwilliammd/iderare-pheno
Project-URL: Changelog, https://github.com/ivanwilliammd/iderare-pheno/blob/main/CHANGELOG.md
Project-URL: Documentation, https://iderare-pheno.readthedocs.io/
Classifier: Intended Audience :: Science/Research
Classifier: Development Status :: 5 - Production/Stable
Classifier: License :: OSI Approved :: BSD License
Classifier: Programming Language :: Python :: 3
Classifier: Topic :: Scientific/Engineering :: Medical Science Apps.
Requires-Python: >=3.10
License-File: LICENSE
Requires-Dist: pandas
Requires-Dist: numpy
Requires-Dist: matplotlib
Requires-Dist: scipy
Requires-Dist: hpo3
Requires-Dist: scikit-learn
Requires-Dist: pyyaml
Provides-Extra: dev
Requires-Dist: ruff; extra == "dev"
Requires-Dist: mypy<1.15,>=1.0; extra == "dev"
Requires-Dist: types-PyYAML; extra == "dev"
Requires-Dist: black<25.0,>=23.0; extra == "dev"
Requires-Dist: black[jupyter]; extra == "dev"
Requires-Dist: isort<5.14,>=5.12; extra == "dev"
Requires-Dist: pytest; extra == "dev"
Requires-Dist: pytest-sphinx; extra == "dev"
Requires-Dist: pytest-cov; extra == "dev"
Requires-Dist: twine>=1.11.0; extra == "dev"
Requires-Dist: build; extra == "dev"
Requires-Dist: setuptools; extra == "dev"
Requires-Dist: wheel; extra == "dev"
Requires-Dist: Sphinx<8.2.0,>=4.3.0; extra == "dev"
Requires-Dist: furo==2024.8.6; extra == "dev"
Requires-Dist: myst-parser<4.1,>=1.0; extra == "dev"
Requires-Dist: sphinx-copybutton==0.5.2; extra == "dev"
Requires-Dist: sphinx-autobuild==2021.3.14; extra == "dev"
Requires-Dist: sphinx-autodoc-typehints==3.0.0; extra == "dev"
Requires-Dist: packaging; extra == "dev"
